{
  "inputFile": "..\\..\\orscf-implementations-dotnet\\(Stage)\\Bin\\ORSCF.StudyManagement.Contract.dll",
  "interfaceTypeNamePattern": "MedicalResearch.StudyManagement.StoreAccess.I*",
  "requireXmlDocForNamespaces": [
    "MedicalResearch.StudyManagement.StoreAccess"
  ],
  "template": "Interfaces",
  "outputLanguage": "PHP",
  "indentDepthPerLevel": 2,
  "codeGenInfoHeader": "based on ORSCF StudyManagement Contract v{InputAssemblyVersion}",
  "outputNamespace": "MedicalResearch.StudyManagement.StoreAccess",
  "customImports": [],
  "modelTypeNameIncludePatterns": [
    "MedicalResearch.StudyManagement.*"
  ],
  "generateTypeNamesInPhp": true,
  "generateDataAnnotationsForLocalModels": true,
  "generateNavigationAnnotationsForLocalModels": false
}